{
  "folder": "YG1nH5ZGeQGZTjFl",
  "name": "Angel's Trumpet",
  "img": "icons/svg/d20-grey.svg",
  "description": "",
  "results": [
    {
      "type": 2,
      "weight": 1,
      "range": [
        1,
        1
      ],
      "drawn": false,
      "text": "Angel's Trumpet",
      "img": "icons/commodities/flowers/lily-grey-orange.webp",
      "documentCollection": "potion-crafting-and-gathering.potion-crafting-and-gathering-ingredients",
      "documentId": "2Q5eat8DBOS7E7Xf",
      "_id": "5afm6LaV4k5j39kj",
      "flags": {
        "better-rolltables": {
          "brt-result-formula": {
            "formula": "1d8"
          }
        }
      },
      "_key": "!tables.results!zeaRezxyo0ePdyXC.5afm6LaV4k5j39kj"
    }
  ],
  "formula": "1",
  "replacement": true,
  "displayRoll": true,
  "sort": 0,
  "ownership": {
    "default": 0
  },
  "flags": {
    "better-rolltables": {
      "tags": "",
      "table-type": "better",
      "table-currency-string": "",
      "loot-amount-key": "",
      "loot-actor-name": ""
    },
    "scene-packer": {
      "hash": "cc6993b67eb405194c27770da33c7c5a825d42e5"
    }
  },
  "_stats": {
    "systemId": "dnd5e",
    "systemVersion": "3.2.0",
    "coreVersion": "11.315",
    "createdTime": 1674400520027,
    "modifiedTime": 1717784812800,
    "lastModifiedBy": "packsbuilder0000"
  },
  "_id": "zeaRezxyo0ePdyXC",
  "_key": "!tables!zeaRezxyo0ePdyXC"
}
