{
  "folder": "YG1nH5ZGeQGZTjFl",
  "name": "Black Cap Mushroom",
  "img": "icons/svg/d20-grey.svg",
  "description": "",
  "results": [
    {
      "type": 2,
      "documentCollection": "potion-crafting-and-gathering.potion-crafting-and-gathering-ingredients",
      "weight": 1,
      "range": [
        1,
        1
      ],
      "drawn": false,
      "text": "Black Cap Mushroom",
      "documentId": "WeMebyyH2jXTQtTH",
      "img": "icons/consumables/mushrooms/ovate-blue.webp",
      "_id": "tbAnYJwSXgHnJPA7",
      "flags": {
        "better-rolltables": {
          "brt-result-formula": {
            "formula": "1d4"
          }
        }
      },
      "_key": "!tables.results!H7zKzMKhS1PRC5LH.tbAnYJwSXgHnJPA7"
    }
  ],
  "formula": "1",
  "replacement": true,
  "displayRoll": true,
  "sort": 0,
  "ownership": {
    "default": 0
  },
  "flags": {
    "better-rolltables": {
      "tags": "",
      "table-type": "better",
      "table-currency-string": "",
      "loot-amount-key": "",
      "loot-actor-name": ""
    },
    "scene-packer": {
      "hash": "81f60d4a87ffe4bd0a4a46383bc316fbbaf38f48"
    }
  },
  "_stats": {
    "systemId": "dnd5e",
    "systemVersion": "3.2.0",
    "coreVersion": "11.315",
    "createdTime": 1674400520027,
    "modifiedTime": 1717784812800,
    "lastModifiedBy": "packsbuilder0000"
  },
  "_id": "H7zKzMKhS1PRC5LH",
  "_key": "!tables!H7zKzMKhS1PRC5LH"
}
