{
  "name": "Nightshade",
  "type": "consumable",
  "img": "icons/consumables/plants/leaf-pink.webp",
  "system": {
    "description": {
      "value": "<p>An inky black flower with purple stalk. It deals 1d4 poison damage when ingested and, on a failed Constitution saving throw, inflicts the poisoned condition for 2d4 hours.</p><section id=\"secret-esMC5MP7JFFwB8jL\" class=\"secret\"><p>Rarity: Uncommon (DC 15)</p><p>Gathering: Herbalism Kit (DC 20)</p><p>Quantity: 1d6 flowers</p><p>Location: Forests</p><p>Uses (3): Potion of Resistance (Necrotic), Basic Poison, Essence of Ether</p></section>",
      "chat": "",
      "unidentified": ""
    },
    "source": "Potion Brewing and Ingredient Gathering for DnD 5e",
    "quantity": 1,
    "weight": 0,
    "price": 10,
    "attunement": 0,
    "equipped": false,
    "rarity": "uncommon",
    "identified": true,
    "activation": {
      "type": "action",
      "cost": 1,
      "condition": ""
    },
    "duration": {
      "value": null,
      "units": ""
    },
    "target": {
      "value": null,
      "width": null,
      "units": "",
      "type": ""
    },
    "range": {
      "value": null,
      "long": null,
      "units": ""
    },
    "uses": {
      "value": 1,
      "max": "1",
      "per": "charges",
      "recovery": "",
      "autoDestroy": true
    },
    "consume": {
      "type": "",
      "target": "",
      "amount": null
    },
    "ability": "",
    "actionType": "save",
    "attackBonus": 0,
    "chatFlavor": "",
    "critical": {
      "threshold": null,
      "damage": ""
    },
    "damage": {
      "parts": [
        [
          "1d4",
          "poison"
        ]
      ],
      "versatile": ""
    },
    "formula": "",
    "save": {
      "ability": "con",
      "dc": 15,
      "scaling": "flat"
    },
    "consumableType": "poison"
  },
  "effects": [
    {
      "label": "Nightshade Poison",
      "icon": "icons/consumables/plants/leaf-pink.webp",
      "origin": "Item.PpZ5ysLIab4PNiCL",
      "duration": {
        "rounds": null,
        "startTime": null,
        "seconds": null,
        "combat": null,
        "turns": null,
        "startRound": null,
        "startTurn": null
      },
      "disabled": false,
      "_id": "4TF9tLteRhEA4Qs2",
      "changes": [
        {
          "key": "StatusEffect",
          "mode": 0,
          "value": "Convenient Effect: Poisoned",
          "priority": 20
        }
      ],
      "tint": null,
      "transfer": false,
      "flags": {
        "dae": {
          "selfTarget": false,
          "selfTargetAlways": false,
          "stackable": "none",
          "durationExpression": "2d4*3600",
          "macroRepeat": "none",
          "specialDuration": []
        },
        "core": {
          "statusId": ""
        }
      },
      "_key": "!items.effects!PpZ5ysLIab4PNiCL.4TF9tLteRhEA4Qs2"
    }
  ],
  "flags": {
    "rest-recovery": {
      "data": {
        "consumable": {
          "enabled": true,
          "dayWorth": false,
          "type": "food"
        },
        "recovery": {
          "enabled": false
        }
      }
    },
    "magicitems": {
      "enabled": false,
      "equipped": false,
      "attuned": false,
      "charges": "0",
      "chargeType": "c1",
      "destroy": false,
      "destroyFlavorText": "reaches 0 charges: it crumbles into ashes and is destroyed.",
      "rechargeable": false,
      "recharge": "0",
      "rechargeType": "t1",
      "rechargeUnit": "r1",
      "sorting": "l"
    },
    "midi-qol": {
      "effectActivation": false
    },
    "midiProperties": {
      "nodam": false,
      "fulldam": true,
      "halfdam": false,
      "rollOther": false,
      "critOther": false,
      "magicdam": false,
      "magiceffect": false,
      "concentration": false,
      "toggleEffect": false
    }
  },
  "_stats": {
    "systemId": "dnd5e",
    "systemVersion": "2.0.3",
    "coreVersion": "10.288",
    "createdTime": 1665866879192,
    "modifiedTime": 1666006615806,
    "lastModifiedBy": "packsbuilder0000"
  },
  "_id": "PpZ5ysLIab4PNiCL",
  "folder": null,
  "sort": 0,
  "ownership": {
    "default": 0
  },
  "_key": "!items!PpZ5ysLIab4PNiCL"
}
