{
  "name": "Gathering: Coast",
  "description": "A random table created from the contents of the Plants Folder.",
  "results": [
    {
      "text": "Dreamlily",
      "type": "pack",
      "img": "icons/commodities/flowers/lily-white.webp",
      "weight": 3,
      "range": [
        2,
        2
      ],
      "drawn": false,
      "documentCollection": "potion-crafting-and-gathering.potion-crafting-and-gathering-ingredients",
      "_id": "PYLJHdmou7ZRtOPj",
      "documentId": "jjxoFljmT5atbIT8",
      "flags": {
        "better-rolltables": {
          "brt-result-formula": {
            "formula": "2d6"
          }
        }
      },
      "_key": "!tables.results!ExBxGVPNbit8FYIz.PYLJHdmou7ZRtOPj"
    },
    {
      "text": "Gillyweed",
      "type": "pack",
      "img": "icons/consumables/plants/basil-herb-green.webp",
      "weight": 3,
      "range": [
        1,
        1
      ],
      "drawn": false,
      "documentCollection": "potion-crafting-and-gathering.potion-crafting-and-gathering-ingredients",
      "_id": "G3FLdLLR9WaSh6Yi",
      "documentId": "kUzQnkx0GC5NTHsv",
      "flags": {
        "better-rolltables": {
          "brt-result-formula": {
            "formula": "2d4"
          }
        }
      },
      "_key": "!tables.results!ExBxGVPNbit8FYIz.G3FLdLLR9WaSh6Yi"
    },
    {
      "text": "Lightning Moss",
      "type": "pack",
      "img": "icons/magic/lightning/barrier-wall-shield-gray.webp",
      "weight": 2,
      "range": [
        3,
        3
      ],
      "drawn": false,
      "documentCollection": "potion-crafting-and-gathering.potion-crafting-and-gathering-ingredients",
      "_id": "hZeN2PpoVMjm5s0y",
      "documentId": "MkUnBgXfcD2QwUwN",
      "flags": {
        "better-rolltables": {
          "brt-result-formula": {
            "formula": "1d6"
          }
        }
      },
      "_key": "!tables.results!ExBxGVPNbit8FYIz.hZeN2PpoVMjm5s0y"
    },
    {
      "text": "White Ghost Orchid Seed",
      "type": "pack",
      "img": "icons/consumables/nuts/cashew-white.webp",
      "weight": 1,
      "range": [
        5,
        5
      ],
      "drawn": false,
      "documentCollection": "potion-crafting-and-gathering.potion-crafting-and-gathering-ingredients",
      "_id": "XBO4nJnVMQkl5lJy",
      "documentId": "AvyiJlB22uJt9J5E",
      "flags": {
        "better-rolltables": {
          "brt-result-formula": {
            "formula": "1d4"
          }
        }
      },
      "_key": "!tables.results!ExBxGVPNbit8FYIz.XBO4nJnVMQkl5lJy"
    },
    {
      "text": "Willowshade Fruit",
      "type": "pack",
      "img": "icons/consumables/fruit/date-ripe-red-green.webp",
      "weight": 2,
      "range": [
        4,
        4
      ],
      "drawn": false,
      "documentCollection": "potion-crafting-and-gathering.potion-crafting-and-gathering-ingredients",
      "_id": "2H8QNwyGP1N077Jc",
      "documentId": "SMab7kAjsYtxGJKJ",
      "flags": {
        "better-rolltables": {
          "brt-result-formula": {
            "formula": "1d8"
          }
        }
      },
      "_key": "!tables.results!ExBxGVPNbit8FYIz.2H8QNwyGP1N077Jc"
    }
  ],
  "formula": "1d5",
  "img": "icons/svg/d20-grey.svg",
  "replacement": true,
  "displayRoll": true,
  "flags": {
    "better-rolltables": {
      "tags": "",
      "table-type": "better",
      "table-currency-string": "",
      "loot-amount-key": "",
      "loot-actor-name": ""
    },
    "hidden-tables": {
      "hidden": false
    }
  },
  "_stats": {
    "systemId": "dnd5e",
    "systemVersion": "2.0.3",
    "coreVersion": "12.327",
    "createdTime": 1665933450716,
    "modifiedTime": 1666008155768,
    "lastModifiedBy": "packsbuilder0000",
    "compendiumSource": null,
    "duplicateSource": null
  },
  "_id": "ExBxGVPNbit8FYIz",
  "folder": null,
  "sort": 0,
  "ownership": {
    "default": 0
  },
  "_key": "!tables!ExBxGVPNbit8FYIz"
}
